pyllm/__init__.py
corellm-0.0.1.dist-info/METADATA
corellm-0.0.1.dist-info/WHEEL
corellm-0.0.1.dist-info/top_level.txt
corellm-0.0.1.dist-info/RECORD
