Metadata-Version: 2.4
Name: corellm
Version: 0.0.1
Summary: An AI library (in development)
Author: Jadon Duff
License: MIT
Project-URL: Homepage, https://github.com/jadonduff/pyllm
Keywords: llm,placeholder
Requires-Python: >=3.8
